MANIFEST.in
README.md
VERSION.txt
setup.py
bin/pandoc-compose
pandoc_compose/__init__.py
pandoc_compose/utils.py
pandoc_compose.egg-info/PKG-INFO
pandoc_compose.egg-info/SOURCES.txt
pandoc_compose.egg-info/dependency_links.txt
pandoc_compose.egg-info/not-zip-safe
pandoc_compose.egg-info/requires.txt
pandoc_compose.egg-info/top_level.txt